{
  "data": [
    {
      "_id": "673eaa1c12224a2b44d1911b",
      "name": "Master bedroom (Singapore)",
      "typeId": "660d73af8a4a6723c905bd0c",
      "typeName": "Expense",
      "categoryId": "673ea65e12224a2b44d1909b",
      "categoryName": "Rent",
      "categoryIcon": "bed-double",
      "currencyId": "6610b4910fcd1af34036ad93",
      "currencyName": "SGD",
      "amount": 1900,
      "description": ""
    },
    {
      "_id": "673eaa3912224a2b44d19120",
      "name": "Netflix",
      "typeId": "660d73af8a4a6723c905bd0c",
      "typeName": "Expense",
      "categoryId": "673ea6c212224a2b44d190a7",
      "categoryName": "Subscription",
      "categoryIcon": "clapperboard",
      "currencyId": "6610b4910fcd1af34036ad93",
      "currencyName": "SGD",
      "amount": 20,
      "description": ""
    }
  ],
  "pagination": {
    "limit": 3,
    "currentPage": 1,
    "totalPages": 1,
    "totalDocuments": 2
  }
}
